<?xml version="1.0" encoding="UTF-8" standalone="yes"?>
<ns3:mets xmlns:ns2="http://www.w3.org/1999/xlink" xmlns:ns3="http://www.loc.gov/METS/" xmlns:xsi="http://www.w3.org/2001/XMLSchema-instance" OBJID="7030191" LABEL="Gongguan sample" PROFILE="TRP_V1" xsi:schemaLocation="http://www.loc.gov/METS/ http://www.loc.gov/standards/mets/mets.xsd">
    <ns3:metsHdr CREATEDATE="2025-03-07T10:10:11.712+01:00" LASTMODDATE="2025-03-07T10:10:11.712+01:00" RECORDSTATUS="SUBMITTED">
        <ns3:agent ROLE="CREATOR" TYPE="ORGANIZATION">
            <ns3:name>UIBK</ns3:name>
            <ns3:note>This METS file was generated by Transkribus</ns3:note>
        </ns3:agent>
    </ns3:metsHdr>
    <ns3:amdSec ID="SOURCE">
        <ns3:sourceMD ID="MD_ORIG">
            <ns3:mdWrap ID="TRP_DOC_MD" MDTYPE="OTHER">
                <ns3:xmlData>
                    <trpDocMetadata>
                        <docId>7030191</docId>
                        <title>Gongguan sample</title>
                        <uploadTimestamp>1740114462969</uploadTimestamp>
                        <uploader>hao_77@outlook.com</uploader>
                        <uploaderId>351529</uploaderId>
                        <nrOfPages>11</nrOfPages>
                        <pageId>91971049</pageId>
                        <url>https://files.transkribus.eu/Get?fileType=view&amp;id=JEERDXZQSDOSQPQDKHMYWQEV</url>
                        <thumbUrl>https://files.transkribus.eu/Get?fileType=thumb&amp;id=JEERDXZQSDOSQPQDKHMYWQEV</thumbUrl>
                        <language></language>
                        <status>0</status>
                        <fimgStoreColl>TrpDoc_DEA_7030191</fimgStoreColl>
                        <localFolder>/mnt/transkribus/export/TRP_EXPORT_3774883345219393474/7030191/Gongguan_sample</localFolder>
                        <origDocId>0</origDocId>
                        <collectionList>
                            <colList>
<colId>1939506</colId>
<colName>Nus1</colName>
<description>Hao_77@outlook.com</description>
<crowdsourcing>false</crowdsourcing>
<elearning>false</elearning>
<nrOfDocuments>0</nrOfDocuments>
<isFavorite>false</isFavorite>
                            </colList>
                        </collectionList>
                        <mainColId>1939506</mainColId>
                    </trpDocMetadata>
                </ns3:xmlData>
            </ns3:mdWrap>
        </ns3:sourceMD>
    </ns3:amdSec>
    <ns3:fileSec>
        <ns3:fileGrp ID="MASTER">
            <ns3:fileGrp ID="IMG">
                <ns3:file ID="IMG_1" SEQ="1" MIMETYPE="image/jpeg" CREATED="2025-02-21T06:08:02.239+01:00" CHECKSUM="68c73041c11769faa033a6d3a7ba003c" CHECKSUMTYPE="MD5">
                    <ns3:FLocat LOCTYPE="OTHER" OTHERLOCTYPE="FILE" ns2:type="simple" ns2:href="0001_p001.jpg"/>
                </ns3:file>
                <ns3:file ID="IMG_2" SEQ="2" MIMETYPE="image/jpeg" CREATED="2025-02-21T06:08:02.619+01:00" CHECKSUM="cd14a9e5106e0657c3b1a13758da66e7" CHECKSUMTYPE="MD5">
                    <ns3:FLocat LOCTYPE="OTHER" OTHERLOCTYPE="FILE" ns2:type="simple" ns2:href="0002_p002.jpg"/>
                </ns3:file>
                <ns3:file ID="IMG_3" SEQ="3" MIMETYPE="image/jpeg" CREATED="2025-02-21T06:08:02.947+01:00" CHECKSUM="9b2a4ff0f402c4e878c85c2bbb6eb51d" CHECKSUMTYPE="MD5">
                    <ns3:FLocat LOCTYPE="OTHER" OTHERLOCTYPE="FILE" ns2:type="simple" ns2:href="0003_p003.jpg"/>
                </ns3:file>
                <ns3:file ID="IMG_4" SEQ="4" MIMETYPE="image/jpeg" CREATED="2025-02-21T06:08:03.273+01:00" CHECKSUM="2487da2c999ccd376569f818c40e0a57" CHECKSUMTYPE="MD5">
                    <ns3:FLocat LOCTYPE="OTHER" OTHERLOCTYPE="FILE" ns2:type="simple" ns2:href="0004_p004.jpg"/>
                </ns3:file>
                <ns3:file ID="IMG_5" SEQ="5" MIMETYPE="image/jpeg" CREATED="2025-02-21T06:08:03.814+01:00" CHECKSUM="e614eb1d7a8a297096c18780e83d90ea" CHECKSUMTYPE="MD5">
                    <ns3:FLocat LOCTYPE="OTHER" OTHERLOCTYPE="FILE" ns2:type="simple" ns2:href="0005_p005.jpg"/>
                </ns3:file>
                <ns3:file ID="IMG_6" SEQ="6" MIMETYPE="image/jpeg" CREATED="2025-02-21T06:08:04.157+01:00" CHECKSUM="cca57181cb0cbc52eaff02dfd6831d1a" CHECKSUMTYPE="MD5">
                    <ns3:FLocat LOCTYPE="OTHER" OTHERLOCTYPE="FILE" ns2:type="simple" ns2:href="0006_p006.jpg"/>
                </ns3:file>
                <ns3:file ID="IMG_7" SEQ="7" MIMETYPE="image/jpeg" CREATED="2025-02-21T06:08:04.487+01:00" CHECKSUM="14dcc0b77425766fcb7ab14276019151" CHECKSUMTYPE="MD5">
                    <ns3:FLocat LOCTYPE="OTHER" OTHERLOCTYPE="FILE" ns2:type="simple" ns2:href="0007_p007.jpg"/>
                </ns3:file>
                <ns3:file ID="IMG_8" SEQ="8" MIMETYPE="image/jpeg" CREATED="2025-02-21T06:08:04.817+01:00" CHECKSUM="53eacb0b9bf69d714d67f5464ac1ee9f" CHECKSUMTYPE="MD5">
                    <ns3:FLocat LOCTYPE="OTHER" OTHERLOCTYPE="FILE" ns2:type="simple" ns2:href="0008_p008.jpg"/>
                </ns3:file>
                <ns3:file ID="IMG_9" SEQ="9" MIMETYPE="image/jpeg" CREATED="2025-02-21T06:08:05.170+01:00" CHECKSUM="0937d1e128a919213b212fec256cd6cc" CHECKSUMTYPE="MD5">
                    <ns3:FLocat LOCTYPE="OTHER" OTHERLOCTYPE="FILE" ns2:type="simple" ns2:href="0009_p009.jpg"/>
                </ns3:file>
                <ns3:file ID="IMG_10" SEQ="10" MIMETYPE="image/jpeg" CREATED="2025-02-21T06:08:05.715+01:00" CHECKSUM="17bbb7cc68d51dd2bb8d99c9328cacb3" CHECKSUMTYPE="MD5">
                    <ns3:FLocat LOCTYPE="OTHER" OTHERLOCTYPE="FILE" ns2:type="simple" ns2:href="0010_p010.jpg"/>
                </ns3:file>
                <ns3:file ID="IMG_11" SEQ="11" MIMETYPE="image/jpeg" CREATED="2025-02-21T06:08:06.254+01:00" CHECKSUM="6ea7382ddc5dd812a59e25c79c02cc47" CHECKSUMTYPE="MD5">
                    <ns3:FLocat LOCTYPE="OTHER" OTHERLOCTYPE="FILE" ns2:type="simple" ns2:href="0011_p011.jpg"/>
                </ns3:file>
            </ns3:fileGrp>
            <ns3:fileGrp ID="PAGEXML">
                <ns3:file ID="PAGEXML_1" SEQ="1" MIMETYPE="application/xml" CREATED="2025-03-07T10:10:28.350+01:00" CHECKSUM="c6123fdf0cbcd32c47a91aa9e52f4379" CHECKSUMTYPE="MD5">
                    <ns3:FLocat LOCTYPE="OTHER" OTHERLOCTYPE="FILE" ns2:type="simple" ns2:href="page/0001_p001.xml"/>
                </ns3:file>
                <ns3:file ID="PAGEXML_2" SEQ="2" MIMETYPE="application/xml" CREATED="2025-03-07T10:10:28.866+01:00" CHECKSUM="b35bfd903b1100f718ae325fdee04473" CHECKSUMTYPE="MD5">
                    <ns3:FLocat LOCTYPE="OTHER" OTHERLOCTYPE="FILE" ns2:type="simple" ns2:href="page/0002_p002.xml"/>
                </ns3:file>
                <ns3:file ID="PAGEXML_3" SEQ="3" MIMETYPE="application/xml" CREATED="2025-03-07T10:10:29.386+01:00" CHECKSUM="5c452e4fbc4445ceb33913a62be5970f" CHECKSUMTYPE="MD5">
                    <ns3:FLocat LOCTYPE="OTHER" OTHERLOCTYPE="FILE" ns2:type="simple" ns2:href="page/0003_p003.xml"/>
                </ns3:file>
                <ns3:file ID="PAGEXML_4" SEQ="4" MIMETYPE="application/xml" CREATED="2025-03-07T10:10:29.898+01:00" CHECKSUM="ed5a2b413aae0c6038dfd2cbbd0f3f53" CHECKSUMTYPE="MD5">
                    <ns3:FLocat LOCTYPE="OTHER" OTHERLOCTYPE="FILE" ns2:type="simple" ns2:href="page/0004_p004.xml"/>
                </ns3:file>
                <ns3:file ID="PAGEXML_5" SEQ="5" MIMETYPE="application/xml" CREATED="2025-03-07T10:10:30.482+01:00" CHECKSUM="217e2e506bb2021861259d1f90328922" CHECKSUMTYPE="MD5">
                    <ns3:FLocat LOCTYPE="OTHER" OTHERLOCTYPE="FILE" ns2:type="simple" ns2:href="page/0005_p005.xml"/>
                </ns3:file>
                <ns3:file ID="PAGEXML_6" SEQ="6" MIMETYPE="application/xml" CREATED="2025-03-07T10:10:31.018+01:00" CHECKSUM="19a04454ca5829d04f340d79a0c67b1f" CHECKSUMTYPE="MD5">
                    <ns3:FLocat LOCTYPE="OTHER" OTHERLOCTYPE="FILE" ns2:type="simple" ns2:href="page/0006_p006.xml"/>
                </ns3:file>
                <ns3:file ID="PAGEXML_7" SEQ="7" MIMETYPE="application/xml" CREATED="2025-03-07T10:10:31.314+01:00" CHECKSUM="45161f0719bb64197187aad716ed015c" CHECKSUMTYPE="MD5">
                    <ns3:FLocat LOCTYPE="OTHER" OTHERLOCTYPE="FILE" ns2:type="simple" ns2:href="page/0007_p007.xml"/>
                </ns3:file>
                <ns3:file ID="PAGEXML_8" SEQ="8" MIMETYPE="application/xml" CREATED="2025-03-07T10:10:31.846+01:00" CHECKSUM="0e2a894328015f7aa62d7d6b7c7850c8" CHECKSUMTYPE="MD5">
                    <ns3:FLocat LOCTYPE="OTHER" OTHERLOCTYPE="FILE" ns2:type="simple" ns2:href="page/0008_p008.xml"/>
                </ns3:file>
                <ns3:file ID="PAGEXML_9" SEQ="9" MIMETYPE="application/xml" CREATED="2025-03-07T10:10:32.146+01:00" CHECKSUM="4a0a7ddd645c6bffa47938c6d0218a4f" CHECKSUMTYPE="MD5">
                    <ns3:FLocat LOCTYPE="OTHER" OTHERLOCTYPE="FILE" ns2:type="simple" ns2:href="page/0009_p009.xml"/>
                </ns3:file>
                <ns3:file ID="PAGEXML_10" SEQ="10" MIMETYPE="application/xml" CREATED="2025-03-07T10:10:32.714+01:00" CHECKSUM="b9b8f4199e186a7b48d5089ffeaf8dae" CHECKSUMTYPE="MD5">
                    <ns3:FLocat LOCTYPE="OTHER" OTHERLOCTYPE="FILE" ns2:type="simple" ns2:href="page/0010_p010.xml"/>
                </ns3:file>
                <ns3:file ID="PAGEXML_11" SEQ="11" MIMETYPE="application/xml" CREATED="2025-03-07T10:10:33.266+01:00" CHECKSUM="fca9a3cab62b812d773cd37d025b7406" CHECKSUMTYPE="MD5">
                    <ns3:FLocat LOCTYPE="OTHER" OTHERLOCTYPE="FILE" ns2:type="simple" ns2:href="page/0011_p011.xml"/>
                </ns3:file>
            </ns3:fileGrp>
        </ns3:fileGrp>
    </ns3:fileSec>
    <ns3:structMap ID="TRP_STRUCTMAP" TYPE="MANUSCRIPT">
        <ns3:div ID="TRP_DOC_DIV" ADMID="MD_ORIG">
            <ns3:div ID="PAGE_1" ORDER="1" TYPE="SINGLE_PAGE">
                <ns3:fptr>
                    <ns3:area FILEID="IMG_1"/>
                </ns3:fptr>
                <ns3:fptr>
                    <ns3:area FILEID="PAGEXML_1"/>
                </ns3:fptr>
            </ns3:div>
            <ns3:div ID="PAGE_2" ORDER="2" TYPE="SINGLE_PAGE">
                <ns3:fptr>
                    <ns3:area FILEID="IMG_2"/>
                </ns3:fptr>
                <ns3:fptr>
                    <ns3:area FILEID="PAGEXML_2"/>
                </ns3:fptr>
            </ns3:div>
            <ns3:div ID="PAGE_3" ORDER="3" TYPE="SINGLE_PAGE">
                <ns3:fptr>
                    <ns3:area FILEID="IMG_3"/>
                </ns3:fptr>
                <ns3:fptr>
                    <ns3:area FILEID="PAGEXML_3"/>
                </ns3:fptr>
            </ns3:div>
            <ns3:div ID="PAGE_4" ORDER="4" TYPE="SINGLE_PAGE">
                <ns3:fptr>
                    <ns3:area FILEID="IMG_4"/>
                </ns3:fptr>
                <ns3:fptr>
                    <ns3:area FILEID="PAGEXML_4"/>
                </ns3:fptr>
            </ns3:div>
            <ns3:div ID="PAGE_5" ORDER="5" TYPE="SINGLE_PAGE">
                <ns3:fptr>
                    <ns3:area FILEID="IMG_5"/>
                </ns3:fptr>
                <ns3:fptr>
                    <ns3:area FILEID="PAGEXML_5"/>
                </ns3:fptr>
            </ns3:div>
            <ns3:div ID="PAGE_6" ORDER="6" TYPE="SINGLE_PAGE">
                <ns3:fptr>
                    <ns3:area FILEID="IMG_6"/>
                </ns3:fptr>
                <ns3:fptr>
                    <ns3:area FILEID="PAGEXML_6"/>
                </ns3:fptr>
            </ns3:div>
            <ns3:div ID="PAGE_7" ORDER="7" TYPE="SINGLE_PAGE">
                <ns3:fptr>
                    <ns3:area FILEID="IMG_7"/>
                </ns3:fptr>
                <ns3:fptr>
                    <ns3:area FILEID="PAGEXML_7"/>
                </ns3:fptr>
            </ns3:div>
            <ns3:div ID="PAGE_8" ORDER="8" TYPE="SINGLE_PAGE">
                <ns3:fptr>
                    <ns3:area FILEID="IMG_8"/>
                </ns3:fptr>
                <ns3:fptr>
                    <ns3:area FILEID="PAGEXML_8"/>
                </ns3:fptr>
            </ns3:div>
            <ns3:div ID="PAGE_9" ORDER="9" TYPE="SINGLE_PAGE">
                <ns3:fptr>
                    <ns3:area FILEID="IMG_9"/>
                </ns3:fptr>
                <ns3:fptr>
                    <ns3:area FILEID="PAGEXML_9"/>
                </ns3:fptr>
            </ns3:div>
            <ns3:div ID="PAGE_10" ORDER="10" TYPE="SINGLE_PAGE">
                <ns3:fptr>
                    <ns3:area FILEID="IMG_10"/>
                </ns3:fptr>
                <ns3:fptr>
                    <ns3:area FILEID="PAGEXML_10"/>
                </ns3:fptr>
            </ns3:div>
            <ns3:div ID="PAGE_11" ORDER="11" TYPE="SINGLE_PAGE">
                <ns3:fptr>
                    <ns3:area FILEID="IMG_11"/>
                </ns3:fptr>
                <ns3:fptr>
                    <ns3:area FILEID="PAGEXML_11"/>
                </ns3:fptr>
            </ns3:div>
        </ns3:div>
    </ns3:structMap>
</ns3:mets>
